LICENSE
README.rst
pyproject.toml
setup.py
Degram/__init__.py
Degram/enums.py
Degram/events.py
Degram/sessions.py
Degram/version.py
Degram.egg-info/PKG-INFO
Degram.egg-info/SOURCES.txt
Degram.egg-info/dependency_links.txt
Degram.egg-info/requires.txt
Degram.egg-info/top_level.txt
Degram/_client/__init__.py
Degram/_client/account.py
Degram/_client/auth.py
Degram/_client/bots.py
Degram/_client/chats.py
Degram/_client/dialogs.py
Degram/_client/downloads.py
Degram/_client/messageparse.py
Degram/_client/messages.py
Degram/_client/telegrambaseclient.py
Degram/_client/telegramclient.py
Degram/_client/updates.py
Degram/_client/uploads.py
Degram/_client/users.py
Degram/_crypto/__init__.py
Degram/_crypto/aes.py
Degram/_crypto/aesctr.py
Degram/_crypto/authkey.py
Degram/_crypto/factorization.py
Degram/_crypto/libssl.py
Degram/_crypto/rsa.py
Degram/_events/__init__.py
Degram/_events/album.py
Degram/_events/base.py
Degram/_events/callbackquery.py
Degram/_events/chataction.py
Degram/_events/inlinequery.py
Degram/_events/messagedeleted.py
Degram/_events/messageedited.py
Degram/_events/messageread.py
Degram/_events/newmessage.py
Degram/_events/raw.py
Degram/_events/userupdate.py
Degram/_events/filters/__init__.py
Degram/_events/filters/base.py
Degram/_events/filters/entities.py
Degram/_events/filters/generic.py
Degram/_events/filters/messages.py
Degram/_misc/__init__.py
Degram/_misc/binaryreader.py
Degram/_misc/enums.py
Degram/_misc/helpers.py
Degram/_misc/hints.py
Degram/_misc/html.py
Degram/_misc/markdown.py
Degram/_misc/messagepacker.py
Degram/_misc/password.py
Degram/_misc/requestiter.py
Degram/_misc/tlobject.py
Degram/_misc/utils.py
Degram/_network/__init__.py
Degram/_network/authenticator.py
Degram/_network/connection.py
Degram/_network/mtprotoplainsender.py
Degram/_network/mtprotosender.py
Degram/_network/mtprotostate.py
Degram/_network/requeststate.py
Degram/_network/transports/__init__.py
Degram/_network/transports/abridged.py
Degram/_network/transports/full.py
Degram/_network/transports/intermediate.py
Degram/_network/transports/transport.py
Degram/_sessions/__init__.py
Degram/_sessions/abstract.py
