Metadata-Version: 2.1
Name: Degram
Version: 0.0.1
Summary: Full-featured Telegram client library for Python 3
Home-page: https://github.com/LonamiWebs/Degram
Author: Lonami Exo
Author-email: totufals@hotmail.com
License: MIT
Download-URL: https://github.com/LonamiWebs/Degram/releases
Keywords: telegram api chat client library messaging mtproto
Platform: UNKNOWN
Classifier: Development Status :: 5 - Production/Stable
Classifier: Intended Audience :: Developers
Classifier: Topic :: Communications :: Chat
Classifier: License :: OSI Approved :: MIT License
Classifier: Programming Language :: Python :: 3
Classifier: Programming Language :: Python :: 3.7
Classifier: Programming Language :: Python :: 3.8
Classifier: Programming Language :: Python :: 3.9
Classifier: Programming Language :: Python :: 3.10
Requires-Python: >=3.7
Provides-Extra: cryptg
License-File: LICENSE
